snippy/__init__.py
snippy/__main__.py
snippy/app.py
py_snippy-1.0.0.dist-info/METADATA
py_snippy-1.0.0.dist-info/WHEEL
py_snippy-1.0.0.dist-info/entry_points.txt
py_snippy-1.0.0.dist-info/top_level.txt
py_snippy-1.0.0.dist-info/RECORD
